moms_apriltag/__init__.py
moms_apriltag/apriltag_drawer.py
moms_apriltag/aruco_tags/__init__.py
moms_apriltag/aruco_tags/calibrate.py
moms_apriltag/color_space.py
moms_apriltag/generator2.py
moms_apriltag/generator3.py
moms_apriltag/tags/__init__.py
moms_apriltag/tags/tag16h5.py
moms_apriltag/tags/tag25h9.py
moms_apriltag/tags/tag36h10.py
moms_apriltag/tags/tag36h11.py
moms_apriltag/tags/tag41h12.py
moms_apriltag/tags/tagCircle21h7.py
moms_apriltag/tags/tagCircle49h12.py
moms_apriltag/tags/tagCustom48h12.py
moms_apriltag/tags/tagStandard41h12.py
moms_apriltag/tags/tagStandard52h13.py
moms_apriltag/target.py
moms_apriltag-2023.1.9.dist-info/LICENSE
moms_apriltag-2023.1.9.dist-info/WHEEL
moms_apriltag-2023.1.9.dist-info/METADATA
moms_apriltag-2023.1.9.dist-info/RECORD
