Metadata-Version: 2.1
Name: moms-apriltag
Version: 2023.1.9
Summary: Generate apriltags, calibration targets, and camera (mono/stereo) calibration
Home-page: https://pypi.org/project/apriltag_gen/
License: MIT
Keywords: apriltag,apriltagv2,apriltagv3,camera,calibration
Author: walchko
Author-email: walchko@users.noreply.github.com
Requires-Python: >=3.8
Classifier: Development Status :: 4 - Beta
Classifier: Framework :: Robot Framework :: Library
Classifier: Intended Audience :: Developers
Classifier: Intended Audience :: Science/Research
Classifier: License :: OSI Approved :: MIT License
Classifier: Natural Language :: English
Classifier: Operating System :: OS Independent
Classifier: Programming Language :: Python :: 3
Classifier: Programming Language :: Python :: 3.8
Classifier: Programming Language :: Python :: 3.9
Classifier: Programming Language :: Python :: 3.10
Classifier: Programming Language :: Python :: 3.11
Classifier: Programming Language :: Python :: 3.10
Classifier: Programming Language :: Python :: 3.11
Classifier: Programming Language :: Python :: 3.8
Classifier: Programming Language :: Python :: 3.9
Classifier: Topic :: Scientific/Engineering
Classifier: Topic :: Scientific/Engineering :: Image Processing
Classifier: Topic :: Software Development :: Libraries
Classifier: Topic :: Software Development :: Libraries :: Application Frameworks
Classifier: Topic :: Software Development :: Libraries :: Python Modules
Requires-Dist: numpy
Requires-Dist: opencv-contrib-python
Project-URL: Repository, https://github.com/MomsFriendlyRobotCompany/apriltag_gen
